cgn_ec/__init__.py
cgn_ec/api.py
cgn_ec/models.py
cgn_ec-0.2.0.dist-info/LICENSE
cgn_ec-0.2.0.dist-info/METADATA
cgn_ec-0.2.0.dist-info/WHEEL
cgn_ec-0.2.0.dist-info/RECORD
